sopel_modules.stocks-1.2.4-py3.9-nspkg.pth
sopel_modules/stocks/__init__.py
sopel_modules/stocks/stocks.py
sopel_modules/stocks/providers/__init__.py
sopel_modules/stocks/providers/alphavantage.py
sopel_modules/stocks/providers/finnhub.py
sopel_modules/stocks/providers/iexcloud.py
sopel_modules.stocks-1.2.4.dist-info/LICENSE
sopel_modules.stocks-1.2.4.dist-info/METADATA
sopel_modules.stocks-1.2.4.dist-info/WHEEL
sopel_modules.stocks-1.2.4.dist-info/namespace_packages.txt
sopel_modules.stocks-1.2.4.dist-info/top_level.txt
sopel_modules.stocks-1.2.4.dist-info/RECORD
