Metadata-Version: 2.2
Name: sopel_modules.stocks
Version: 1.2.4
Summary: Sopel Stocks Plugin
Home-page: http://github.com/rustybower/sopel-stocks
Author: Rusty Bower
Author-email: rusty@rustybower.com
License: MIT License
License-File: LICENSE
Requires-Dist: requests
Dynamic: author
Dynamic: author-email
Dynamic: description
Dynamic: description-content-type
Dynamic: home-page
Dynamic: license
Dynamic: requires-dist
Dynamic: summary
